savant_models/__init__.py
savant_models/config.py
savant_models/batch_management_models/__init__.py
savant_models/batch_management_models/enums/__init__.py
savant_models/batch_management_models/enums/batch_sort_by.py
savant_models/batch_management_models/enums/batch_type.py
savant_models/batch_management_models/enums/internal_external_batch.py
savant_models/batch_management_models/enums/project_batch.py
savant_models/batch_management_models/enums/stereo_orientation_enum.py
savant_models/batch_management_models/enums/type_of_annotation_enum.py
savant_models/batch_management_models/models/__init__.py
savant_models/batch_management_models/models/batch.py
savant_models/batch_management_models/models/batch_frontend.py
savant_models/batch_management_models/models/batch_statistics.py
savant_models/batch_management_models/models/batch_summary.py
savant_models/batch_management_models/models/batches_by_type.py
savant_models/batch_management_models/models/sub_models/__init__.py
savant_models/batch_management_models/models/sub_models/canvas_controls.py
savant_models/batch_management_models/models/sub_models/configuration.py
savant_models/batch_management_models/models/sub_models/patch_configuration.py
savant_models/file_management_models/__init__.py
savant_models/file_management_models/enums/__init__.py
savant_models/file_management_models/enums/workflow_enum.py
savant_models/file_management_models/models/__init__.py
savant_models/file_management_models/models/s3_file_info.py
savant_models/file_management_models/models/workflow_trigger.py
savant_models/file_project_management_models/enums/__init__.py
savant_models/file_project_management_models/enums/file_project_type.py
savant_models/file_project_management_models/models/__init__.py
savant_models/file_project_management_models/models/file_project.py
savant_models/file_project_management_models/models/parts.py
savant_models/file_project_management_models/models/s3_file_project.py
savant_models-1.0.13.dist-info/LICENSE
savant_models-1.0.13.dist-info/METADATA
savant_models-1.0.13.dist-info/WHEEL
savant_models-1.0.13.dist-info/top_level.txt
savant_models-1.0.13.dist-info/RECORD
