Metadata-Version: 2.2
Name: savant_models
Version: 1.0.13
Summary: A small example package
Author-email: SAVANT <savantmdt@gmail.com>
Project-URL: repo, https://bitbucket.org/realtimeml/savant-models/src/main/
Classifier: Programming Language :: Python :: 3
Classifier: License :: OSI Approved :: MIT License
Classifier: Operating System :: OS Independent
Requires-Python: >=3.9
License-File: LICENSE
Requires-Dist: fastapi==0.115.6
Requires-Dist: pydantic==2.10.5
Requires-Dist: pydantic_core==2.27.2
Requires-Dist: pymongo==4.9.2
